README.rst
setup.py
src/scripts/zas
src/scripts/zas.py
src/zas.egg-info/PKG-INFO
src/zas.egg-info/SOURCES.txt
src/zas.egg-info/dependency_links.txt
src/zas.egg-info/requires.txt
src/zas.egg-info/top_level.txt
src/zascore/__init__.py
src/zascore/core.py
test/test.py