Metadata-Version: 1.1
Name: zas
Version: 0.1.1
Summary: Zencore Application Server.
Home-page: https://github.com/appstore-zencore/zas
Author: zencore
Author-email: dobetter@zencore.cn
License: MIT
Keywords: zas
Platform: UNKNOWN
Classifier: Development Status :: 5 - Production/Stable
Classifier: Intended Audience :: Developers
Classifier: Topic :: Software Development :: Libraries :: Python Modules
Classifier: License :: OSI Approved :: MIT License
Classifier: Programming Language :: Python :: 3
Classifier: Programming Language :: Python :: 3 :: Only
Requires: click
Requires: pyyaml
Requires: zdas
Requires: zencore_utils
